README.md
setup.py
hawksoft/__init__.py
hawksoft/md2zhihu.py
hawksoft/rename.py
hawksoft/selmv.py
hawksoft/tree.py
hawksoft.tools.egg-info/PKG-INFO
hawksoft.tools.egg-info/SOURCES.txt
hawksoft.tools.egg-info/dependency_links.txt
hawksoft.tools.egg-info/entry_points.txt
hawksoft.tools.egg-info/top_level.txt