Metadata-Version: 2.1
Name: hawksoft.tools
Version: 1.1.3
Summary: Provides many useful command lines in python
Home-page: https://github.com/xingyongkang
Author: xingyongkang
Author-email: xingyongkang@cqu.edu.cn
License: MIT
Keywords: md2zhihu tree selmv
Platform: any
